data/__init__.py
data/money/__init__.py
data/money/de.json
data/money/es.json
data/money/eur_min.json
data/money/fr.json
data/money/nl.json
data/money/us.json
data/money/us_min.json
natura/__init__.py
natura/__main__.py
natura/classes.py
natura/conversion_backends.py
natura/finder.py
natura/scanner.py
natura/utils.py
natura-0.0.65.dist-info/METADATA
natura-0.0.65.dist-info/WHEEL
natura-0.0.65.dist-info/entry_points.txt
natura-0.0.65.dist-info/top_level.txt
natura-0.0.65.dist-info/RECORD
